smb_lib/__init__.py
smb_lib/smbLib.py
smb_lib-0.1.7.dist-info/LICENSE.txt
smb_lib-0.1.7.dist-info/METADATA
smb_lib-0.1.7.dist-info/WHEEL
smb_lib-0.1.7.dist-info/top_level.txt
smb_lib-0.1.7.dist-info/RECORD
