Metadata-Version: 2.1
Name: smb-lib
Version: 0.1.7
Summary: save librairie python
Home-page: https://github.com/clement-alexandre/TotemBionet
Author: Mohamed Chennouf
Author-email: mohamed.chennouf@etu.unice.fr
License: WTFPL
Keywords: jupyter,biology
Platform: UNKNOWN
Classifier: Intended Audience :: Science/Research
Classifier: Topic :: Scientific/Engineering :: Bio-Informatics
Classifier: Programming Language :: Python :: 3.6
Classifier: Programming Language :: Python :: 3.7
Requires-Dist: requests
